ovos_openai_plugin-2.0.6.dist-info/licenses/LICENSE
ovos_solver_openai_persona/__init__.py
ovos_solver_openai_persona/dialog_transformers.py
ovos_solver_openai_persona/engines.py
ovos_solver_openai_persona/summarizer.py
ovos_solver_openai_persona/version.py
ovos_openai_plugin-2.0.6.dist-info/METADATA
ovos_openai_plugin-2.0.6.dist-info/WHEEL
ovos_openai_plugin-2.0.6.dist-info/entry_points.txt
ovos_openai_plugin-2.0.6.dist-info/top_level.txt
ovos_openai_plugin-2.0.6.dist-info/zip-safe
ovos_openai_plugin-2.0.6.dist-info/RECORD
