Metadata-Version: 2.4
Name: ovos_openai_plugin
Version: 2.0.6
Summary: A question solver plugin for ovos
Home-page: https://github.com/OpenVoiceOS/ovos-solver-plugin-openai-persona
Author: jarbasai
Author-email: jarbasai@mailfence.com
License: MIT
Keywords: ovos plugin utterance fallback query
License-File: LICENSE
Requires-Dist: requests
Requires-Dist: ovos-plugin-manager<3.0.0,>=0.0.26
Dynamic: author
Dynamic: author-email
Dynamic: description
Dynamic: description-content-type
Dynamic: home-page
Dynamic: keywords
Dynamic: license
Dynamic: license-file
Dynamic: requires-dist
Dynamic: summary
